{
    "type": "Feature",
    "properties": {},
    "geometry": {
        "type": "Polygon",
        "coordinates": [
            [
                [
                    1.910551614,
                    42.344029908
                ],
                [
                    1.754695964,
                    42.348851759
                ],
                [
                    1.030411231,
                    42.447150378
                ],
                [
                    1.030777447,
                    42.45085832
                ],
                [
                    1.031433585,
                    42.452628367
                ],
                [
                    1.032410163,
                    42.45444419
                ],
                [
                    1.039246204,
                    42.461280232
                ],
                [
                    1.041519799,
                    42.463538567
                ],
                [
                    1.910551614,
                    42.344029908
                ]
            ]
        ]
    }
}